lixinger-0.1.11.dist-info/METADATA
lixinger-0.1.11.dist-info/WHEEL
lixinger/__init__.py
lixinger/api/__init__.py
lixinger/api/cn/__init__.py
lixinger/api/cn/company/__init__.py
lixinger/api/cn/company/base.py
lixinger/api/cn/company/block_deal.py
lixinger/api/cn/company/candlestick.py
lixinger/api/cn/company/dividend_and_alloment.py
lixinger/api/cn/company/equity_change.py
lixinger/api/cn/company/fundamental_non_financial.py
lixinger/api/cn/company/fundamental_statistics.py
lixinger/api/cn/company/indices.py
lixinger/api/cn/company/industries.py
lixinger/api/cn/company/pledge.py
lixinger/api/cn/company/senior_executive_shares_change.py
lixinger/api/cn/company/shareholders_num.py
lixinger/api/cn/fund/__init__.py
lixinger/api/cn/fund/exchange_traded_close_price.py
lixinger/api/cn/fund/total_net_value.py
lixinger/api/cn/index/__init__.py
lixinger/api/cn/index/base.py
lixinger/api/cn/index/candlestick.py
lixinger/api/cn/index/constituents.py
lixinger/api/cn/index/drawdown.py
lixinger/api/cn/index/fundamental.py
lixinger/api/hk/__init__.py
lixinger/api/macro/__init__.py
lixinger/api/us/__init__.py
lixinger/client.py
lixinger/config.py
lixinger/py.typed
lixinger/settings.toml
lixinger/utils.py
lixinger-0.1.11.dist-info/RECORD
