Metadata-Version: 2.1
Name: lixinger
Version: 0.1.11
Summary: Lixinger SDK for Python (Unofficial)
Keywords: lixinger
Author-Email: Chaoying <chaoying2022@gmail.com>
License: MIT
Classifier: Programming Language :: Python :: 3
Classifier: Programming Language :: Python :: 3.8
Classifier: Programming Language :: Python :: 3.9
Classifier: Programming Language :: Python :: 3.10
Classifier: Programming Language :: Python :: 3.11
Project-URL: Homepage, https://github.com/Chaoyingz/lixinger
Project-URL: Repository, https://github.com/Chaoyingz/lixinger
Requires-Python: >=3.8
Requires-Dist: pandera>=0.14.5
Requires-Dist: pydantic>=1.10.7
Requires-Dist: requests>=2.29.0
Requires-Dist: dynaconf>=3.1.12
Requires-Dist: tenacity>=8.2.2
